{"v":4,"entries":{"checkbox--docs":{"id":"checkbox--docs","title":"Checkbox","name":"Docs","importPath":"./.storybook/Checkbox.stories.jsx","type":"docs","tags":["docs","autodocs"],"storiesImports":[]},"checkbox--checkbox-list":{"type":"story","id":"checkbox--checkbox-list","name":"Checkbox List","title":"Checkbox","importPath":"./.storybook/Checkbox.stories.jsx","tags":["story"]},"checkbox--with-checked":{"type":"story","id":"checkbox--with-checked","name":"With Checked","title":"Checkbox","importPath":"./.storybook/Checkbox.stories.jsx","tags":["story"]},"form--docs":{"id":"form--docs","title":"Form","name":"Docs","importPath":"./.storybook/Form.stories.jsx","type":"docs","tags":["docs","autodocs"],"storiesImports":[]},"form--demo":{"type":"story","id":"form--demo","name":"Demo","title":"Form","importPath":"./.storybook/Form.stories.jsx","tags":["story"]},"input--docs":{"id":"input--docs","title":"Input","name":"Docs","importPath":"./.storybook/Input.stories.jsx","type":"docs","tags":["docs","autodocs"],"storiesImports":[]},"input--input-text":{"type":"story","id":"input--input-text","name":"Input Text","title":"Input","importPath":"./.storybook/Input.stories.jsx","tags":["story"]},"input--input-with-label-text":{"type":"story","id":"input--input-with-label-text","name":"Input With Label Text","title":"Input","importPath":"./.storybook/Input.stories.jsx","tags":["story"]},"input--input-with-no-label-text":{"type":"story","id":"input--input-with-no-label-text","name":"Input With No Label Text","title":"Input","importPath":"./.storybook/Input.stories.jsx","tags":["story"]},"input--input-as-text-area":{"type":"story","id":"input--input-as-text-area","name":"Input As Text Area","title":"Input","importPath":"./.storybook/Input.stories.jsx","tags":["story"]},"input--input-as-password":{"type":"story","id":"input--input-as-password","name":"Input As Password","title":"Input","importPath":"./.storybook/Input.stories.jsx","tags":["story"]},"radio--docs":{"id":"radio--docs","title":"Radio","name":"Docs","importPath":"./.storybook/Radio.stories.jsx","type":"docs","tags":["docs","autodocs"],"storiesImports":[]},"radio--radio-list":{"type":"story","id":"radio--radio-list","name":"Radio List","title":"Radio","importPath":"./.storybook/Radio.stories.jsx","tags":["story"]},"radio--with-checked":{"type":"story","id":"radio--with-checked","name":"With Checked","title":"Radio","importPath":"./.storybook/Radio.stories.jsx","tags":["story"]},"select--docs":{"id":"select--docs","title":"Select","name":"Docs","importPath":"./.storybook/Select.stories.jsx","type":"docs","tags":["docs","autodocs"],"storiesImports":[]},"select--select-list":{"type":"story","id":"select--select-list","name":"Select List","title":"Select","importPath":"./.storybook/Select.stories.jsx","tags":["story"]},"select--with-selcted":{"type":"story","id":"select--with-selcted","name":"With Selcted","title":"Select","importPath":"./.storybook/Select.stories.jsx","tags":["story"]}}}
